bayesian_models/__init__.py
bayesian_models/core.py
bayesian_models/data.py
bayesian_models/math.py
bayesian_models/models.py
bayesian_models/typing.py
bayesian_models/utilities.py
bayesian_models-0.1.3.dist-info/LICENSE
bayesian_models-0.1.3.dist-info/METADATA
bayesian_models-0.1.3.dist-info/WHEEL
bayesian_models-0.1.3.dist-info/top_level.txt
bayesian_models-0.1.3.dist-info/RECORD
