Metadata-Version: 2.1
Name: bayesian-models
Version: 0.1.3
Summary: A package for building common bayesian models in pymc
Author-email: Alexander Rodis <alexanderrhodis@gmail.com>
Maintainer-email: Alexander Rodis <alexanderrhodis@gmail.com>
Project-URL: Homepage, https://github.com/AlexRodis/bayesian_models
Project-URL: Bug Tracker, https://github.com/AlexRodis/bayesian_models/issues
Project-URL: Documentation, https://bayesian-models.readthedocs.io/en/latest/
Keywords: bayesian,models,statistics,pymc
Classifier: Programming Language :: Python :: 3
Classifier: Operating System :: OS Independent
Classifier: License :: OSI Approved :: Apache Software License
Classifier: Development Status :: 5 - Production/Stable
Classifier: Intended Audience :: Science/Research
Classifier: Intended Audience :: Healthcare Industry
Classifier: Intended Audience :: Developers
License-File: LICENSE
Requires-Dist: pyinterval (>=1.2)
Requires-Dist: pymc (>=5.1.2)
Requires-Dist: scikit-learn (>=1.2)
Provides-Extra: gpu
Requires-Dist: jax ; extra == 'gpu'
Requires-Dist: jaxlib ; extra == 'gpu'
Requires-Dist: numpyro ; extra == 'gpu'
Provides-Extra: dev
Requires-Dist: sphinx ; extra == 'dev'
Requires-Dist: sphinxcontrib-katex ; extra == 'dev'
Requires-Dist: sphinx-rtd-theme ; extra == 'dev'
